pip_compile_cross_platform/__init__.py
pip_compile_cross_platform/__main__.py
pip_compile_cross_platform-1.4.2.dist-info/entry_points.txt
pip_compile_cross_platform-1.4.2.dist-info/LICENSE
pip_compile_cross_platform-1.4.2.dist-info/METADATA
pip_compile_cross_platform-1.4.2.dist-info/WHEEL
pip_compile_cross_platform-1.4.2.dist-info/RECORD
