Metadata-Version: 2.1
Name: pip-compile-cross-platform
Version: 1.4.2
Summary: Lock your dependencies once, use your lockfile everywhere
Home-page: https://gitlab.com/mitchhentges/pip-compile-cross-platform
License: AGPL-3.0-only
Author: Mitchell Hentges
Author-email: mitch9654@gmail.com
Requires-Python: >=3.8.1,<4.0.0
Classifier: Development Status :: 4 - Beta
Classifier: Intended Audience :: Developers
Classifier: Intended Audience :: System Administrators
Classifier: License :: OSI Approved :: GNU Affero General Public License v3
Classifier: Operating System :: OS Independent
Classifier: Programming Language :: Python :: 3
Classifier: Programming Language :: Python :: 3.9
Classifier: Programming Language :: Python :: 3.10
Classifier: Programming Language :: Python :: 3.11
Classifier: Programming Language :: Python :: 3.12
Classifier: Topic :: System :: Systems Administration
Requires-Dist: pip-requirements-parser (>=32.0.0,<33.0.0)
Requires-Dist: poetry (>=1.8.1,<2.0.0)
Requires-Dist: poetry-core (>=1.9.0,<2.0.0)
Requires-Dist: poetry-plugin-export (>=1.6.0,<2.0.0)
Project-URL: Repository, https://gitlab.com/mitchhentges/pip-compile-cross-platform
